Workbook

Sheet README
A1: Token Optimization Cloud — Business Model
A3: Companion to docs/TOKEN-OPTIMIZATION-BUSINESS-MODEL.md and the five-doc research series.
A4: Five-year (2026–2030) bottoms-up market sizing and revenue model for the outcome-verified
A5: token optimizer for coding-agent fleets (savings-share + Pro subscriptions + platform fees).
A7: TABS
A8: Assumptions — every driver of the model. Edit these; everything else recalculates.
A9: Market — TAM / SAM / SOM by year, built from the assumptions.
A10: Revenue — three penetration scenarios (Conservative / Base / Aggressive) by revenue stream.
A11: UnitEcon — gross margin and an illustrative enterprise-customer P&L.
A12: Comps — grounding data points and sources for every external number.
A14: LEGEND
A15: Blue text = hardcoded input (edit me) Black text = formula (leave alone)
... A20: unless the row header says otherwise.

Sheet Assumptions
A1: Assumptions — all model drivers
A2: Blue = edit; yellow = key levers. Basis / source noted in column G.
A4: Per-year drivers | B4: 2026 | C4: 2027 | D4: 2028 | E4: 2029 | F4: 2030
A5: Professional developers worldwide (M) | B5: 32 | C5: 34 | D5: 36 | E5: 38 | F5: 40 | G5: Industry estimates cluster ~30–35M in 2026 (SlashData/Evans-class), ~2M/yr net growth.
A6: % using agentic coding tools | B6: 0.3 | C6: 0.42 | D6: 0.54 | E6: 0.63 | F6: 0.7 | G6: 90% use some AI tool, 51% daily (2026 surveys, Comps tab); agentic (not autocomplete) share ramps toward daily-use share.
A7: Agentic-coding developers (M) | B7: =B5*B6 -> 9.6 | C7: =C5*C6 -> 14.28 | D7: =D5*D6 -> 19.44 | E7: =E5*E6 -> 23.94 | F7: =F5*F6 -> 28 | G7: Formula: devs x agentic %
A8: API-metered (enterprise) share of agentic devs | B8: 0.25 | C8: 0.3 | D8: 0.35 | E8: 0.4 | F8: 0.45 | G8: Rest are on capped subscriptions ($20–200/mo). Enterprises shift to metered as usage scales (Uber/Microsoft cost episodes, Comps).
A9: API-metered devs (M) | B9: =B7*B8 -> 2.4 | C9: =C7*C8 -> 4.284 | D9: =D7*D8 -> 6.804 | E9: =E7*E8 -> 9.576 | F9: =F7*F8 -> 12.6 | G9: Formula: agentic x metered share
A10: Subscription-capped devs (M) | B10: =B7-B9 -> 7.2 | C10: =C7-C9 -> 9.996 | D10: =D7-D9 -> 12.636 | E10: =E7-E9 -> 14.364 | F10: =F7-F9 -> 15.4 | G10: Formula: agentic minus metered
A11: Avg monthly API spend per metered dev ($) | B11: 150 | C11: 165 | D11: 180 | E11: 195 | F11: 210 | G11: Anthropic enterprise data: $150–250/dev/mo typical (2026). Net +~9%/yr: usage up sharply, unit prices down (Gartner).
A13: Single levers (apply to all years)
A14: Gateway-addressable share of metered API spend | B14: 0.65 | G14: Feasibility doc §3.4: Claude Code + Codex API lanes fully addressable; Cursor agent-mode BYO-key partially; OAuth lanes excluded.
A15: Achievable verified savings rate (on addressable spend) | B15: 0.18 | G15: CodexZero repeated bench: 15% lossless, score parity. Cache shaping adds upside (ProjectDiscovery cut 59–70%). 18% is conservative blended.
A16: Savings-share take rate | B16: 0.2 | G16: FinOps comps: nOps ~15% of savings; Zesty 10–20%; Usage.ai % of delivered savings. 20% mid-range.
A17: Pro subscription price ($/mo) | B17: 15 | G17: Under the noise floor of what it saves an individual (research doc §7.2).
A18: Pro attach ceiling (% of subscription-capped devs) | B18: 0.08 | G18: SAM ceiling for individual conversion; developer-tool paid-attach norms low single digits to ~10%.
A19: Enterprise platform fee ($/dev/mo) | B19: 10 | G19: SLA/SSO/dashboard seat floor alongside savings-share (two-track FinOps pricing pattern).
A20: % of enterprise (metered) devs on paid platform tier | B20: 0.6 | G20: Share of covered enterprise seats that take the platform tier vs savings-share only.
A21: COGS as % of revenue | B21: 0.15 | G21: Proxy compute, artifact storage, eval/shadow compute. Gateway COGS is small; evals dominate.

Sheet Market
A1: Market sizing — TAM / SAM / SOM ($M unless noted)
B3: 2026 | C3: 2027 | D3: 2028 | E3: 2029 | F3: 2030
A4: TAM
A5: Coding-agent API (metered) spend ($M/yr) | B5: =Assumptions!B9*Assumptions!B11*12 -> 4320 | C5: =Assumptions!C9*Assumptions!C11*12 -> 8482.32 | D5: =Assumptions!D9*Assumptions!D11*12 -> 14696.64 | E5: =Assumptions!E9*Assumptions!E11*12 -> 22407.84 | F5: =Assumptions!F9*Assumptions!F11*12 -> 31752
A6: Subscription-lane spend ($M/yr, at $35/mo blended) | B6: =Assumptions!B10*35*12 -> 3024 | C6: =Assumptions!C10*35*12 -> 4198.32 | D6: =Assumptions!D10*35*12 -> 5307.12 | E6: =Assumptions!E10*35*12 -> 6032.88 | F6: =Assumptions!F10*35*12 -> 6468
A7: Total coding-agent spend TAM ($M/yr) | B7: =B5+B6 -> 7344 | C7: =C5+C6 -> 12680.64 | D7: =D5+D6 -> 20003.76 | E7: =E5+E6 -> 28440.72 | F7: =F5+F6 -> 38220
A9: SAM (our monetizable revenue pool)
A10: Addressable metered spend ($M/yr) | B10: =B5*Assumptions!$B$14 -> 2808 | C10: =C5*Assumptions!$B$14 -> 5513.508 | D10: =D5*Assumptions!$B$14 -> 9552.816 | E10: =E5*Assumptions!$B$14 -> 14565.096 | F10: =F5*Assumptions!$B$14 -> 20638.8
A11: Verified-savings pool created for customers ($M/yr) | B11: =B10*Assumptions!$B$15 -> 505.44 | C11: =C10*Assumptions!$B$15 -> 992.43144 | D11: =D10*Assumptions!$B$15 -> 1719.5069 | E11: =E10*Assumptions!$B$15 -> 2621.7173 | F11: =F10*Assumptions!$B$15 -> 3714.984
A12: Savings-share revenue pool ($M/yr) | B12: =B11*Assumptions!$B$16 -> 101.088 | C12: =C11*Assumptions!$B$16 -> 198.48629 | D12: =D11*Assumptions!$B$16 -> 343.90138 | E12: =E11*Assumptions!$B$16 -> 524.34346 | F12: =F11*Assumptions!$B$16 -> 742.9968
A13: Pro subscription revenue pool ($M/yr) | B13: =Assumptions!B10*Assumptions!$B$18*Assumptions!$B$17*12 -> 103.68 | C13: =Assumptions!C10*Assumptions!$B$18*Assumptions!$B$17*12 -> 143.9424 | D13: =Assumptions!D10*Assumptions!$B$18*Assumptions!$B$17*12 -> 181.9584 | E13: =Assumptions!E10*Assumptions!$B$18*Assumptions!$B$17*12 -> 206.8416 | F13: =Assumptions!F10*Assumptions!$B$18*Assumptions!$B$17*12 -> 221.76
A14: Enterprise platform-fee revenue pool ($M/yr) | B14: =Assumptions!B9*Assumptions!$B$19*12*Assumptions!$B$20 -> 172.8 | C14: =Assumptions!C9*Assumptions!$B$19*12*Assumptions!$B$20 -> 308.448 | D14: =Assumptions!D9*Assumptions!$B$19*12*Assumptions!$B$20 -> 489.888 | E14: =Assumptions!E9*Assumptions!$B$19*12*Assumptions!$B$20 -> 689.472 | F14: =Assumptions!F9*Assumptions!$B$19*12*Assumptions!$B$20 -> 907.2
A15: Total SAM ($M/yr) | B15: =B12+B13+B14 -> 377.568 | C15: =C12+C13+C14 -> 650.87669 | D15: =D12+D13+D14 -> 1015.7478 | E15: =E12+E13+E14 -> 1420.6571 | F15: =F12+F13+F14 -> 1871.9568
A17: SOM = scenario penetration x SAM — see Revenue tab
A19: Cross-check: metered TAM 2030 vs enterprise-LLM market forecasts ($5.9B 2025 -> $91.5B 2036 at 28.3% CAGR;
A20: inference = 85% of enterprise AI budgets; coding agents are the largest agentic workload). See Comps tab.

Sheet Revenue
A1: Revenue scenarios — SOM by stream ($M)
A2: Penetration = share of each SAM pool captured. Blue rows are scenario levers.
A4: Conservative | B4: 2026 | C4: 2027 | D4: 2028 | E4: 2029 | F4: 2030
A5: Penetration of SAM | B5: 0.001 | C5: 0.0025 | D5: 0.005 | E5: 0.0075 | F5: 0.01
A6: Savings-share revenue | B6: =Market!B12*B5 -> 0.101088 | C6: =Market!C12*C5 -> 0.49621572 | D6: =Market!D12*D5 -> 1.7195069 | E6: =Market!E12*E5 -> 3.9325759 | F6: =Market!F12*F5 -> 7.429968
A7: Pro subscription revenue | B7: =Market!B13*B5 -> 0.10368 | C7: =Market!C13*C5 -> 0.359856 | D7: =Market!D13*D5 -> 0.909792 | E7: =Market!E13*E5 -> 1.551312 | F7: =Market!F13*F5 -> 2.2176
A8: Enterprise platform fees | B8: =Market!B14*B5 -> 0.1728 | C8: =Market!C14*C5 -> 0.77112 | D8: =Market!D14*D5 -> 2.44944 | E8: =Market!E14*E5 -> 5.17104 | F8: =Market!F14*F5 -> 9.072
A9: Total revenue ($M) | B9: =SUM(B6:B8) -> 0.377568 | C9: =SUM(C6:C8) -> 1.6271917 | D9: =SUM(D6:D8) -> 5.0787389 | E9: =SUM(E6:E8) -> 10.654928 | F9: =SUM(F6:F8) -> 18.719568
A10: Customer savings delivered ($M) | B10: =Market!B11*B5 -> 0.50544 | C10: =Market!C11*C5 -> 2.4810786 | D10: =Market!D11*D5 -> 8.5975344 | E10: =Market!E11*E5 -> 19.66288 | F10: =Market!F11*F5 -> 37.14984
A11: YoY growth | B11: n/a | C11: =IF(B9=0,0,C9/B9-1) -> 3.3096653 | D11: =IF(C9=0,0,D9/C9-1) -> 2.1211681 | E11: =IF(D9=0,0,E9/D9-1) -> 1.0979476 | F11: =IF(E9=0,0,F9/E9-1) -> 0.75689297
A13: Base | B13: 2026 | C13: 2027 | D13: 2028 | E13: 2029 | F13: 2030
A14: Penetration of SAM | B14: 0.003 | C14: 0.008 | D14: 0.015 | E14: 0.022 | F14: 0.03
A15: Savings-share revenue | B15: =Market!B12*B14 -> 0.303264 | C15: =Market!C12*C14 -> 1.5878903 | D15: =Market!D12*D14 -> 5.1585206 | E15: =Market!E12*E14 -> 11.535556 | F15: =Market!F12*F14 -> 22.289904
A16: Pro subscription revenue | B16: =Market!B13*B14 -> 0.31104 | C16: =Market!C13*C14 -> 1.1515392 | D16: =Market!D13*D14 -> 2.729376 | E16: =Market!E13*E14 -> 4.5505152 | F16: =Market!F13*F14 -> 6.6528
A17: Enterprise platform fees | B17: =Market!B14*B14 -> 0.5184 | C17: =Market!C14*C14 -> 2.467584 | D17: =Market!D14*D14 -> 7.34832 | E17: =Market!E14*E14 -> 15.168384 | F17: =Market!F14*F14 -> 27.216
A18: Total revenue ($M) | B18: =SUM(B15:B17) -> 1.132704 | C18: =SUM(C15:C17) -> 5.2070135 | D18: =SUM(D15:D17) -> 15.236217 | E18: =SUM(E15:E17) -> 31.254455 | F18: =SUM(F15:F17) -> 56.158704
A19: Customer savings delivered ($M) | B19: =Market!B11*B14 -> 1.51632 | C19: =Market!C11*C14 -> 7.9394515 | D19: =Market!D11*D14 -> 25.792603 | E19: =Market!E11*E14 -> 57.67778 | F19: =Market!F11*F14 -> 111.44952
A20: YoY growth | B20: n/a | C20: =IF(B18=0,0,C18/B18-1) -> 3.5969764 | D20: =IF(C18=0,0,D18/C18-1) -> 1.9260951 | E20: =IF(D18=0,0,E18/D18-1) -> 1.0513265 | F20: =IF(E18=0,0,F18/E18-1) -> 0.79682236
A22: Aggressive | B22: 2026 | C22: 2027 | D22: 2028 | E22: 2029 | F22: 2030
A23: Penetration of SAM | B23: 0.008 | C23: 0.02 | D23: 0.04 | E23: 0.06 | F23: 0.08
A24: Savings-share revenue | B24: =Market!B12*B23 -> 0.808704 | C24: =Market!C12*C23 -> 3.9697258 | D24: =Market!D12*D23 -> 13.756055 | E24: =Market!E12*E23 -> 31.460607 | F24: =Market!F12*F23 -> 59.439744
A25: Pro subscription revenue | B25: =Market!B13*B23 -> 0.82944 | C25: =Market!C13*C23 -> 2.878848 | D25: =Market!D13*D23 -> 7.278336 | E25: =Market!E13*E23 -> 12.410496 | F25: =Market!F13*F23 -> 17.7408
A26: Enterprise platform fees | B26: =Market!B14*B23 -> 1.3824 | C26: =Market!C14*C23 -> 6.16896 | D26: =Market!D14*D23 -> 19.59552 | E26: =Market!E14*E23 -> 41.36832 | F26: =Market!F14*F23 -> 72.576
A27: Total revenue ($M) | B27: =SUM(B24:B26) -> 3.020544 | C27: =SUM(C24:C26) -> 13.017534 | D27: =SUM(D24:D26) -> 40.629911 | E27: =SUM(E24:E26) -> 85.239423 | F27: =SUM(F24:F26) -> 149.75654
A28: Customer savings delivered ($M) | B28: =Market!B11*B23 -> 4.04352 | C28: =Market!C11*C23 -> 19.848629 | D28: =Market!D11*D23 -> 68.780275 | E28: =Market!E11*E23 -> 157.30304 | F28: =Market!F11*F23 -> 297.19872
A29: YoY growth | B29: n/a | C29: =IF(B27=0,0,C27/B27-1) -> 3.3096653 | D29: =IF(C27=0,0,D27/C27-1) -> 2.1211681 | E29: =IF(D27=0,0,E27/D27-1) -> 1.0979476 | F29: =IF(E27=0,0,F27/E27-1) -> 0.75689297

Sheet UnitEcon
A1: Unit economics
A3: Company level (Base scenario, 2030)
A4: Revenue ($M) | B4: =Revenue!F18 -> 56.158704
A5: COGS ($M) | B5: =B4*Assumptions!$B$21 -> 8.4238056
A6: Gross profit ($M) | B6: =B4-B5 -> 47.734898
A7: Gross margin | B7: =IF(B4=0,0,B6/B4) -> 0.85
A9: Illustrative enterprise customer (annual)
A10: Developers on metered API | B10: 500 | C10: Mid-size enterprise engineering org.
A11: Monthly API spend per dev ($) | B11: 175 | C11: Within Anthropic's observed $150–250 band.
A12: Annual coding-agent API spend ($) | B12: =B10*B11*12 -> 1050000
A13: Addressable spend ($) | B13: =B12*Assumptions!$B$14 -> 682500
A14: Verified savings delivered ($) | B14: =B13*Assumptions!$B$15 -> 122850
A15: Savings-share revenue ($) | B15: =B14*Assumptions!$B$16 -> 24570
A16: Platform fees ($) | B16: =B10*Assumptions!$B$19*12*Assumptions!$B$20 -> 36000
A17: Total ACV ($) | B17: =B15+B16 -> 60570
A18: Customer net saving after our fees ($) | B18: =B14-B17+B16 -> 98280 | C18: Savings minus savings-share (platform fee buys SLA/SSO/dashboards, shown separately).
A20: Customers implied (Base 2030): revenue / ACV | B20: =IF(B17=0,0,Revenue!F18*1000000/B17) -> 927.17028 | C20: PLG motion: pip-install wedge -> Pro -> team workspace -> enterprise (research doc §7.1–7.2). CAC is dominated by content + community, not sales, until enterprise stage.

Sheet Comps
A1: Grounding data and comparables (all figures as reported by cited sources)
A3: Data point | B3: Figure | C3: Source
A4: Enterprise LLM market, 2025 -> 2036 | B4: $5.9B -> $91.5B (28.3% CAGR) | C4: Future Market Insights, enterprise LLM market report
A5: Inference share of enterprise AI budgets, 2026 | B5: ~85%; 2nd-largest line item after talent | C5: NeuralWired / Gartner 2026 coverage
A6: Avg enterprise monthly AI spend, 2025 | B6: $85,521 (+36% YoY) | C6: Tokonomics LLM cost management guide 2026
A7: Per-developer AI consumption growth | B7: ~18.6x in 9 months (agentic tools) | C7: getdx.com AI assistant pricing/ROI guide 2026
A8: Per-employee AI spend, 2026 (anticipated) | B8: ~$2,068 | C8: Atlanta Fed via greyjournal.net 2026
A9: Claude Code enterprise cost per dev | B9: $150–250/mo typical; power users $500–2,000 | C9: Anthropic enterprise data via morphllm.com 2026
A10: Tokens per agentic task | B10: 400k–2M; agentic = 5–30x chatbot tokens | C10: morphllm.com; oplexa.com inference cost 2026
A11: Cost-pressure episodes | B11: Uber exhausted annual AI coding budget by Aug 2026; Microsoft curtailed internal Claude Code | C11: oplexa.com / NeuralWired 2026
A12: Developer AI adoption | B12: 90% use AI at work; 51% daily; Copilot 20M+ users; Claude Code used by 63% of teams | C12: JetBrains 2026 survey; digitalapplied.com; axis-intelligence.com
A13: Proven lossless savings (one agent, local) | B13: 15% fewer tokens, identical 29/36 score | C13: Retro2512/CodexZero terminal-bench replication
A14: Proven cache-shaping savings | B14: 7% -> 84% cache hit rate; 59–70% total spend cut | C14: ProjectDiscovery case via ofox.ai 2026
... A20: Gateway market structure, 2026 | B20: Per-token markups raced to zero across major gateways | C20: klymentiev.com gateway guide 2026
